tqdist.cpython-38-darwin.so
tqdist-1.1.dist-info/METADATA
tqdist-1.1.dist-info/WHEEL
tqdist-1.1.dist-info/top_level.txt
tqdist-1.1.dist-info/RECORD
